spylon_kernel/__init__.py
spylon_kernel/__main__.py
spylon_kernel/_scala_interpreter.py
spylon_kernel/init_spark_magic.py
spylon_kernel/scala_kernel.py
spylon_kernel/scala_magic.py
spylon_kernel-0.0.1.dist-info/DESCRIPTION.rst
spylon_kernel-0.0.1.dist-info/METADATA
spylon_kernel-0.0.1.dist-info/RECORD
spylon_kernel-0.0.1.dist-info/WHEEL
spylon_kernel-0.0.1.dist-info/metadata.json
spylon_kernel-0.0.1.dist-info/top_level.txt
