Metadata-Version: 2.0
Name: spylon-kernel
Version: 0.0.1
Summary: Jupyter metakernel for apache spark and scala
Home-page: http://github.com/mariusvniekerk/spylon-kernel
Author: Marius van Niekerk
Author-email: marius.v.niekerk+spylon@gmail.com
License: MIT
Platform: UNKNOWN
Classifier: Intended Audience :: Developers
Classifier: Intended Audience :: System Administrators
Classifier: Intended Audience :: Science/Research
Classifier: License :: OSI Approved :: MIT License
Classifier: Programming Language :: Python
